[
    {
        "message": "Come to Central Park."
    },
    {
        "message": "Even if you say that."
    },
    {
        "message": "How am I supposed to search in such a vast place?"
    },
    {
        "message": "If they’re filming, they should be noticeable."
    },
    {
        "message": "Ah, over there!"
    },
    {
        "message": "It's my first time seeing the film crew up close."
    },
    {
        "message": "Fabar."
    },
    {
        "message": "Hey, you’re late; I was waiting with my neck stretched out."
    },
    {
        "message": "Jake."
    },
    {
        "message": "Sorry for being late."
    },
    {
        "message": "Fabar."
    },
    {
        "message": "No need to worry about it. I wasn’t just sitting around without doing anything."
    },
    {
        "message": "Jake."
    },
    {
        "message": "I’m sorry."
    },
    {
        "message": "Fabar."
    },
    {
        "message": "You said you were free, but you sure look busy. So, I hear you're working on Meryl’s request?"
    },
    {
        "message": "Jake."
    },
    {
        "message": "Um, who told you that?"
    },
    {
        "message": "Fabar."
    },
    {
        "message": "It's Meryl. I don’t know what she requested, though."
    },
    {
        "message": "Jake."
    },
    {
        "message": "Oh, from her directly?"
    },
    {
        "message": "I thought it was Yuriko spreading the word."
    },
    {
        "message": "Fabar."
    },
    {
        "message": "By the way, what did Meryl request?"
    },
    {
        "message": "Jake."
    },
    {
        "message": "In this world, it’s the rule not to reveal the client's secrets."
    },
    {
        "message": "Fabar."
    },
    {
        "message": "Yeah, you’re right. Just like in dramas and movies, as expected of a detective."
    },
    {
        "message": "Jake."
    },
    {
        "message": "Uh, hmm."
    },
    {
        "message": "I can’t tell if I’m being complimented or insulted."
    },
    {
        "message": "　　See　　"
    },
    {
        "message": "　　Talk　　"
    },
    {
        "message": "　　Hear　　"
    },
    {
        "message": "　　Think　　"
    },
    {
        "message": "　System　"
    },
    {
        "message": "　　The situation around　　"
    },
    {
        "message": "　Director Fabar　"
    },
    {
        "message": "　　Gloria　　"
    },
    {
        "message": "　Director Fabar　"
    },
    {
        "message": "　　Gloria　　"
    },
    {
        "message": "　About Cindy　"
    },
    {
        "message": "About Director Fabar"
    },
    {
        "message": "　About Gloria　"
    },
    {
        "message": "　About Cindy　"
    },
    {
        "message": "　　　Save　　　"
    },
    {
        "message": "Exit the game"
    },
    {
        "message": "Gloria"
    },
    {
        "message": "Please contact me if you find Cindy. The phone number is 378-9646. We can discuss rewards then."
    },
    {
        "message": "Jake"
    },
    {
        "message": "Uh, um"
    },
    {
        "message": "Ignoring my controlling voice, she strode away."
    },
    {
        "message": "Fabar"
    },
    {
        "message": "Have we come to an agreement?"
    },
    {
        "message": "Jake"
    },
    {
        "message": "Uh, yeah."
    },
    {
        "message": "Well."
    },
    {
        "message": "Fabar"
    },
    {
        "message": "Do your best, detective. It's no exaggeration to say that the fate of this movie rests on your shoulders."
    },
    {
        "message": "Fabar"
    },
    {
        "message": "Without Cindy, filming won't proceed."
    },
    {
        "message": "Jake"
    },
    {
        "message": "I'll try my best."
    },
    {
        "message": "Fabar"
    },
    {
        "message": "Yeah, I’m counting on you."
    },
    {
        "message": "The location shoot is still in progress. It's my first time encountering a scene like this, so I’m a bit excited."
    },
    {
        "message": "It's from situations like this that movies are made."
    },
    {
        "message": "。"
    },
    {
        "message": "The director seems to be as energetic as ever. He might be the type who gets pumped up when shooting starts."
    },
    {
        "message": "He has a gentle smile, but I've heard he can be scary during filming."
    },
    {
        "message": "He might be wearing a gloomy expression because Cindy is gone."
    },
    {
        "message": "But this might be his serious face."
    },
    {
        "message": "With his eyes narrowed more tightly, he looks angry."
    },
    {
        "message": "He seems to dislike me, but is that why he’s making such a sour face?"
    },
    {
        "message": "Jake"
    },
    {
        "message": "By the way, what was your request?"
    },
    {
        "message": "?"
    },
    {
        "message": "Fabar"
    },
    {
        "message": "Actually,"
    },
    {
        "message": "well, it’s quicker to just talk to the person directly. Hey, Gloria!"
    },
    {
        "message": "Gloria"
    },
    {
        "message": "Fabar"
    },
    {
        "message": "So, Gloria, make sure you take care of it."
    },
    {
        "message": "Jake"
    },
    {
        "message": "Um, what kind of matter is it?"
    },
    {
        "message": "Gloria"
    },
    {
        "message": "Just remember, I never thought I’d ask you for something."
    },
    {
        "message": "Jake"
    },
    {
        "message": "Then you don’t have to force me; I wasn't plotting to get work from the director."
    },
    {
        "message": "Gloria"
    },
    {
        "message": "Even if I’m not inclined, I can't help but follow the director's orders."
    },
    {
        "message": "Jake"
    },
    {
        "message": "Huh, is that how it works?"
    },
    {
        "message": "Gloria"
    },
    {
        "message": "That's how it is."
    },
    {
        "message": "Gloria"
    },
    {
        "message": "Anyway, that’s why you should go find Cindy."
    },
    {
        "message": "Jake"
    },
    {
        "message": "Huh?"
    },
    {
        "message": "Gloria"
    },
    {
        "message": "Are you hard of hearing? I said to look for Cindy. That's the request."
    },
    {
        "message": "Gloria"
    },
    {
        "message": "I wonder if you'll actually be able to find her?"
    },
    {
        "message": "Jake"
    },
    {
        "message": "Cindy's gone, huh?"
    },
    {
        "message": "Gloria"
    },
    {
        "message": "That's why I put out the request, right?"
    },
    {
        "message": "Jake"
    },
    {
        "message": "Yeah, that's true, but—"
    },
    {
        "message": "Gloria"
    },
    {
        "message": "I really think she's hiding somewhere in New York, but I just can't figure out where she is."
    },
    {
        "message": "Jake"
    },
    {
        "message": "Is there anything else?"
    },
    {
        "message": "Gloria"
    },
    {
        "message": "I think she looks really different without her usual face. She looks much younger."
    },
    {
        "message": "Gloria"
    },
    {
        "message": "He's a skilled detective, so he should be able to find her right away."
    },
    {
        "message": "Does that mean the director passed the job to you?"
    },
    {
        "message": "Whatever his intentions are, I'm sure he's seen as the guy who got work from Gloria thanks to the director's favor."
    },
    {
        "message": "That's probably the misunderstanding."
    },
    {
        "message": "He must've wanted to be involved with detectives too."
    },
    {
        "message": "That same sulky face from the party."
    },
    {
        "message": "It makes me feel like he did something bad."
    },
    {
        "message": "You'd think he'd be more frazzled if Cindy's gone, but—"
    },
    {
        "message": "Surprisingly, he looks calm."
    },
    {
        "message": "Could it be that he has some idea of where Cindy went?"
    },
    {
        "message": "Either way, this just gave me another job."
    },
    {
        "message": "From Gloria's reaction, I can't imagine she was kidnapped; it feels more like she left of her own accord."
    },
    {
        "message": "Is it possible she went missing because the work was too tough, wanting to return to being a normal girl?"
    },
    {
        "message": "I wonder why Cindy disappeared."
    },
    {
        "message": "It's not like she wanted to run away from Gloria, right?"
    },
    {
        "message": "※※※ This is a bug ※※※"
    },
    {
        "message": "Ｖ＝"
    },
    {
        "message": "　Ｎ＝"
    }
]