[
    {
        "message": "Jake"
    },
    {
        "message": "Yuriko"
    },
    {
        "message": "Kristy"
    },
    {
        "message": "Serial Murder Case"
    },
    {
        "message": "It's better to leave him alone for now."
    },
    {
        "message": "What about Guy? Isn't Guy with you?"
    },
    {
        "message": "Sorry, unfortunately, Guy isn't with us."
    },
    {
        "message": "No, no! I can't go without Guy."
    },
    {
        "message": "You can't come in without him."
    },
    {
        "message": "Now, go home! It would be a big deal if bad rumors spread."
    },
    {
        "message": "Should we come back later?"
    },
    {
        "message": "Please bring Guy! I want to talk to Guy, hurry and bring him!"
    }
]