[
    {
        "message": "Jake"
    },
    {
        "message": "Eva"
    },
    {
        "message": "Kristy"
    },
    {
        "message": "Andy"
    },
    {
        "message": "Y-Yeah"
    },
    {
        "message": "W-Well, I'm glad to see you again."
    },
    {
        "message": "Y-Yeah"
    },
    {
        "message": "We've been seeing each other a lot lately, huh?"
    },
    {
        "message": "I-I feel like I've made a friend, and I'm really happy about it."
    },
    {
        "message": "S-Sorry."
    },
    {
        "message": "I-I still haven't gone back."
    },
    {
        "message": "I haven't returned yet."
    },
    {
        "message": "Ah."
    },
    {
        "message": "We've been seeing each other a lot lately."
    },
    {
        "message": "I mean, you're just always around, huh?"
    },
    {
        "message": "Ah, sorry for saying something weird."
    },
    {
        "message": "Ah,"
    },
    {
        "message": "!"
    },
    {
        "message": "S-Should I make some coffee?"
    },
    {
        "message": "Hey!"
    },
    {
        "message": "How are you?"
    },
    {
        "message": "Y-Yeah."
    },
    {
        "message": "I'm really glad you came to visit."
    },
    {
        "message": "　　See　　"
    },
    {
        "message": "　　Talk　　"
    },
    {
        "message": "　　Listen　　"
    },
    {
        "message": "　　Think　　"
    },
    {
        "message": "　Move　"
    },
    {
        "message": "　System　"
    },
    {
        "message": "　　Surroundings　　"
    },
    {
        "message": "　　Guy　　"
    },
    {
        "message": "About him　　"
    },
    {
        "message": "Regarding　him　"
    },
    {
        "message": "　　The article　　"
    },
    {
        "message": "　　Guy　　"
    },
    {
        "message": "the　matter　of　　"
    },
    {
        "message": "the matter of　"
    },
    {
        "message": "the matter of　"
    },
    {
        "message": "　　The article　　"
    },
    {
        "message": "　　to another place　　"
    },
    {
        "message": "　　　Save　　　"
    },
    {
        "message": "to exit the game"
    },
    {
        "message": "On the desk, there are piles of binders and dictionaries related to documents, while"
    },
    {
        "message": "the desk is neatly organized."
    },
    {
        "message": "This editing room is a very small room, and perhaps"
    },
    {
        "message": "it might be a room allocated as a personal workspace."
    },
    {
        "message": "Despite its cute appearance, the inside feels grimy and looks like it could collapse any moment."
    },
    {
        "message": "He sits there, skinny and hunched over, always looking anxious."
    },
    {
        "message": "His eyes are vacant and never meet mine."
    },
    {
        "message": "I wonder how he manages to keep this job with a personality like that."
    },
    {
        "message": "It's like"
    },
    {
        "message": "he's a servant to someone."
    },
    {
        "message": "I'm really happy when he comes around."
    },
    {
        "message": "R-really?"
    },
    {
        "message": "However, I’ve been getting rejected quite spectacularly lately."
    },
    {
        "message": "I guess I'm being turned down."
    },
    {
        "message": "He’s busy, all fired up to finish writing a new article. But I don’t know what kind of article it is."
    },
    {
        "message": "I wonder where he’s gone."
    },
    {
        "message": "It's a shame my friend is here, but..."
    },
    {
        "message": "Ah,"
    },
    {
        "message": "I wish you would come back soon."
    },
    {
        "message": "I wonder what you are up to."
    },
    {
        "message": "Lately, you haven't been around."
    },
    {
        "message": "I haven't been able to see you, huh?"
    },
    {
        "message": "You're talking smoothly today, huh?"
    },
    {
        "message": "Y-Yeah."
    },
    {
        "message": "I,"
    },
    {
        "message": "seem to have gotten used to you."
    },
    {
        "message": "I've gotten used to it."
    },
    {
        "message": "?"
    },
    {
        "message": "I'm really shy,"
    },
    {
        "message": "but,"
    },
    {
        "message": "I'm used to it now."
    },
    {
        "message": "Let's keep being good friends from now on."
    },
    {
        "message": "Ah, yeah."
    },
    {
        "message": "I’ll be your friend no matter what kind of person you are."
    },
    {
        "message": "Having more friends makes every day happy."
    },
    {
        "message": "H-Hey."
    },
    {
        "message": "But there's no one around. I've been pretty unlucky lately."
    },
    {
        "message": "When you say that, I start to feel like I'm a pretty unlucky person."
    },
    {
        "message": "R-Really? I'm special!"
    },
    {
        "message": "Deep."
    },
    {
        "message": "I didn't really mean anything by it."
    },
    {
        "message": "I-I’m in trouble."
    },
    {
        "message": "I hope I’m not being misunderstood."
    },
    {
        "message": "Misunderstood?"
    },
    {
        "message": "I-I."
    },
    {
        "message": "J-"
    },
    {
        "message": "ust."
    },
    {
        "message": "I don’t think you’re a bad person."
    },
    {
        "message": "Ah, thanks?"
    },
    {
        "message": "I'm glad."
    },
    {
        "message": "Even so,"
    },
    {
        "message": "it's late, huh?"
    },
    {
        "message": "Hello,"
    },
    {
        "message": "how have you been?"
    },
    {
        "message": "You've come again, huh?"
    },
    {
        "message": "I wanted to ask you something."
    },
    {
        "message": "Don't you have a girlfriend?"
    },
    {
        "message": "Huh,"
    },
    {
        "message": "well,"
    },
    {
        "message": "um,"
    },
    {
        "message": "i-it’s a secret, you know."
    },
    {
        "message": "I don’t really care, but are you scared to talk to me?"
    },
    {
        "message": "N-no."
    },
    {
        "message": "W-well, it's just that,"
    },
    {
        "message": "I get nervous around unfamiliar people."
    },
    {
        "message": "I-I guess you don’t know when he’ll come back, right?"
    },
    {
        "message": "Y-yeah."
    },
    {
        "message": "I-I don’t know when he’ll be back."
    },
    {
        "message": "Should I come back later?"
    },
    {
        "message": "Y-yeah."
    },
    {
        "message": "I-I think that would be a wise choice."
    },
    {
        "message": "Right."
    },
    {
        "message": "S-sorry."
    },
    {
        "message": "I-I just don’t like telling people what I’m doing."
    },
    {
        "message": "Hey,"
    },
    {
        "message": "do you think I’m close with Guy?"
    },
    {
        "message": "Hmm, I wonder? That’s something I want to ask you."
    },
    {
        "message": "Y-yeah, that’s true."
    },
    {
        "message": "W-well, it’s not something I should be concerned about."
    },
    {
        "message": "Isn't it?"
    },
    {
        "message": "Uh, there’s nothing to worry about."
    },
    {
        "message": "Is there some concern about Guy?"
    },
    {
        "message": "Um, no."
    },
    {
        "message": "N-no, not at all."
    },
    {
        "message": "I just, well,"
    },
    {
        "message": "I thought about it."
    },
    {
        "message": "a little."
    },
    {
        "message": "It’s just somehow on my mind."
    },
    {
        "message": "Could it be,"
    },
    {
        "message": "you"
    },
    {
        "message": "like him?"
    },
    {
        "message": "Huh, n-no way."
    },
    {
        "message": "No way."
    },
    {
        "message": "I can't believe I a am"
    },
    {
        "message": "could"
    },
    {
        "message": "do something that would make you angry."
    },
    {
        "message": "It, it must be."
    },
    {
        "message": "Y-you like a manly guy like Guy."
    },
    {
        "message": "By the way,"
    },
    {
        "message": "didn't you say something about Guy's trip?"
    },
    {
        "message": "Guy's trip?"
    },
    {
        "message": "?　N-no,"
    },
    {
        "message": "I-I don't know about that."
    },
    {
        "message": "You really don't know?"
    },
    {
        "message": "S-sorry!"
    },
    {
        "message": "I'm useless."
    },
    {
        "message": "As for Guy,"
    },
    {
        "message": "he knows all about it."
    },
    {
        "message": "For sure. I somehow think so."
    },
    {
        "message": "E, uh,"
    },
    {
        "message": "he is"
    },
    {
        "message": "out interviewing."
    },
    {
        "message": "I see, that's a shame."
    },
    {
        "message": "M-maybe,"
    },
    {
        "message": "did you come to ask me out on a date?"
    },
    {
        "message": "Hey,"
    },
    {
        "message": "I think it's better to not ask him out."
    },
    {
        "message": "Don't worry, I have no such intentions."
    },
    {
        "message": "N-no such intentions, huh?"
    },
    {
        "message": "Y-you are"
    },
    {
        "message": "Are you making fun of (me)?!"
    },
    {
        "message": "She"
    },
    {
        "message": "is, a wonderful woman."
    },
    {
        "message": "And I met her"
    },
    {
        "message": "at Guy's apartment, but I wonder if she's planning to write another article about Guy?"
    },
    {
        "message": "Well,"
    },
    {
        "message": "I don't know anything."
    },
    {
        "message": "I really don't know anything."
    },
    {
        "message": "I hope she comes back soon,"
    },
    {
        "message": "but."
    },
    {
        "message": "That person is Guy's"
    },
    {
        "message": "fiancée, isn't she?"
    },
    {
        "message": "Ah, that's right."
    },
    {
        "message": "So, so"
    },
    {
        "message": "does he dislike her?"
    },
    {
        "message": "I wonder why he dislikes her; I probably can't like her either."
    },
    {
        "message": "?"
    },
    {
        "message": "That's a pretty harsh thing to say about a stranger."
    },
    {
        "message": "I've seen her,"
    },
    {
        "message": "I have seen her."
    },
    {
        "message": "She came to yell at us before."
    },
    {
        "message": "I don't"
    },
    {
        "message": "like hysterical women."
    },
    {
        "message": "You know?"
    },
    {
        "message": "I wonder if she's going to write another article about (him)?"
    },
    {
        "message": "Well,"
    },
    {
        "message": "I'm just helping out,"
    },
    {
        "message": "you see,"
    },
    {
        "message": "I'm useless, after all."
    },
    {
        "message": "You probably know more about her,"
    },
    {
        "message": "right?"
    },
    {
        "message": "Right now,"
    },
    {
        "message": "now"
    },
    {
        "message": "What kind of article are you in charge of?"
    },
    {
        "message": "N-no, the article is a secret from everyone."
    },
    {
        "message": "I-it's a secret!"
    },
    {
        "message": "You don’t need to yell about it."
    },
    {
        "message": "I’m not asking you to give me all the details."
    },
    {
        "message": "B-but."
    },
    {
        "message": "You can’t say that, or else."
    },
    {
        "message": "I’ll get in trouble."
    },
    {
        "message": "I’ll be in big trouble."
    },
    {
        "message": "I’m really sorryyyy."
    },
    {
        "message": "There’s nothing I can tell you."
    },
    {
        "message": "I-I’m useless, and."
    },
    {
        "message": "I don’t know anything."
    },
    {
        "message": "Who knows where Gai went,"
    },
    {
        "message": "wouldn't know that, right?"
    },
    {
        "message": "likes Gai,"
    },
    {
        "message": "but hey, maybe that could actually be a thing."
    },
    {
        "message": "Gai might actually be a surprisingly popular guy."
    },
    {
        "message": "seems to know where Gai is headed."
    },
    {
        "message": "Still, what does it mean that he hasn't come back in a month?"
    },
    {
        "message": "Where on earth did Guy go?"
    },
    {
        "message": "I came all this way to visit."
    },
    {
        "message": "He must be out."
    },
    {
        "message": "But what should I even talk about"
    },
    {
        "message": "when I meet up with him?"
    },
    {
        "message": "I don't think there's anything fun to talk about with that woman."
    },
    {
        "message": "Surprisingly"
    },
    {
        "message": "their desktop is tidy. They seem to be the type who keeps information and everything else neatly organized."
    },
    {
        "message": "It's true that people can be surprising."
    },
    {
        "message": "Nevertheless,"
    },
    {
        "message": "I wonder when she will come back?"
    },
    {
        "message": "She definitely knows about Guy's trip. But why does she know so much about him?"
    },
    {
        "message": "I wonder if Guy and I are in a close relationship?"
    },
    {
        "message": "His attitude is different from before."
    },
    {
        "message": "It feels like he's gotten fond of me."
    },
    {
        "message": "The conversation is becoming easier to understand,"
    },
    {
        "message": "but just a bit."
    },
    {
        "message": "- Porter"
    },
    {
        "message": "He's still in a rigid state."
    },
    {
        "message": "I think he can relax and act normally when I'm not looking, but for some reason, he stiffens up in front of me."
    },
    {
        "message": "Rigid state and speech impediment."
    },
    {
        "message": "It’s probably a technique caused by excessive tension, but why does it only happen with me?"
    },
    {
        "message": "He."
    },
    {
        "message": "He really gets defensive when it comes to that."
    },
    {
        "message": "He might like him."
    },
    {
        "message": "Seeing his attitude makes me feel like I'm doing something wrong."
    },
    {
        "message": "Come to think of it, this editorial department is"
    },
    {
        "message": "where I was brought."
    },
    {
        "message": "Guy"
    },
    {
        "message": "dislikes him because he's Guy's fiancée?"
    },
    {
        "message": "I see, thinking that way makes it all add up."
    },
    {
        "message": "Wait, no way"
    },
    {
        "message": "right?"
    },
    {
        "message": "I wonder how"
    },
    {
        "message": "is doing right now?"
    },
    {
        "message": "I can't believe he knows about the article."
    },
    {
        "message": "It seems I can't get anything out of him."
    },
    {
        "message": "※※※ It's a bug ※※※"
    },
    {
        "message": "Ｖ＝"
    },
    {
        "message": "　Ｎ＝"
    }
]