[
    {
        "message": "Jake"
    },
    {
        "message": "Yuriko"
    },
    {
        "message": "　Next week　"
    },
    {
        "message": "At this time, Guy and the others must have already set off."
    },
    {
        "message": "They told me this morning they would be heading out in the evening, so it was sudden."
    },
    {
        "message": "I didn’t even get to ask where they were going."
    },
    {
        "message": "Without Guy, it’s so quiet here."
    },
    {
        "message": "　　　　　　　Bam bam bam"
    },
    {
        "message": "Huh."
    },
    {
        "message": "Have they already come back?"
    },
    {
        "message": "　　　　　　　　　　Bang!"
    },
    {
        "message": "B-boss, it’s a major crisis! A major crisis!"
    },
    {
        "message": "What’s going on? You’re so loud just coming back."
    },
    {
        "message": "That’s because—"
    },
    {
        "message": "That’s because!"
    },
    {
        "message": "Ha, whee, ha, whee."
    },
    {
        "message": "　　See.　　"
    },
    {
        "message": "　　Talk.　　"
    },
    {
        "message": "　　Listen.　　"
    },
    {
        "message": "　System.　"
    },
    {
        "message": "　　Check the surroundings.　　"
    },
    {
        "message": "　What happened?　"
    },
    {
        "message": "　　About Guy.　　"
    },
    {
        "message": "　About Kristy.　"
    },
    {
        "message": "　　　Save.　　　"
    },
    {
        "message": "Exit the game."
    },
    {
        "message": "Boss!"
    },
    {
        "message": "Isn’t everyone involved in the incidents happening in New York someone we know?"
    },
    {
        "message": "That’s true. Ever since being invited to the Fabar director’s party in Boston, things have been going downhill."
    },
    {
        "message": "Guy and the others seem suspicious too."
    },
    {
        "message": "Detective Cosner."
    },
    {
        "message": "You’re the one who’s suspicious."
    },
    {
        "message": "Detective Maurice"
    },
    {
        "message": "Hello, I let myself in since the door wasn't locked."
    },
    {
        "message": "Hello."
    },
    {
        "message": "What can I do for you today? Is it about the case of Ginny being found?"
    },
    {
        "message": "Detective Maurice"
    },
    {
        "message": "Oh, you already knew that. As expected from a detective."
    },
    {
        "message": "Come on, I was the one who told you. If you're going to compliment someone, make sure it's me."
    },
    {
        "message": "Cosner"
    },
    {
        "message": "Hey there, you’ve managed to stay safe so far. Or are you perhaps the killer's girlfriend?"
    },
    {
        "message": "That's rude; I don't deserve to be called a killer."
    },
    {
        "message": "Detective Maurice"
    },
    {
        "message": "Well, that’s a valid point. You haven't been confirmed as the killer yet."
    },
    {
        "message": "Huh?"
    },
    {
        "message": "Detective Maurice"
    },
    {
        "message": "Mr. Snipes, I apologize, but could you accompany us to the station?"
    },
    {
        "message": "W-Wait, why?"
    },
    {
        "message": "?"
    },
    {
        "message": "Cosner"
    },
    {
        "message": "Listen, kid, this guy is actually the fearsome serial murder case suspect. You've been lucky to have made it this far."
    },
    {
        "message": "Wait a second, I didn't do anything like that."
    },
    {
        "message": "Detective Maurice"
    },
    {
        "message": "I’m sorry, but I don’t want to resort to rough methods. Please cooperate and we can speak comfortably at the station."
    },
    {
        "message": "Cosner"
    },
    {
        "message": "Hey, don’t you think it’d be better to just knock him out? Nobody's going to complain about hitting a scumbag like this."
    },
    {
        "message": "They will, and I'll be the one saying it, trust me!"
    },
    {
        "message": "Be quiet. Fine, there’s nothing I need to hide. If we talk, you’ll understand."
    },
    {
        "message": "Detective Maurice"
    },
    {
        "message": "I apologize."
    },
    {
        "message": "Outside, it was almost time to be enveloped by dusk."
    },
    {
        "message": "Cosner"
    },
    {
        "message": "Hehe, being too honest is a bit scary, don’t you think, old man?"
    },
    {
        "message": "Detective Maurice"
    },
    {
        "message": "I'm sorry it has turned out this way. However, if you can prove your innocence at the station, you can go home right away."
    },
    {
        "message": "This is my first time in a police station. If I think of it as a field trip, it feels a lot more relaxed."
    },
    {
        "message": "Cosner"
    },
    {
        "message": "What do you mean relaxed, you idiot! I'm the kind of persistent snake of a man. I'll uncover all your crimes."
    },
    {
        "message": "Cosner"
    },
    {
        "message": "Come on, get in the car quickly!"
    },
    {
        "message": "Right in front of me,"
    },
    {
        "message": "is standing in my way."
    },
    {
        "message": "Inside the room,"
    },
    {
        "message": "the smell of the buns bought earlier is wafting."
    },
    {
        "message": "Despite having run here out of breath, the usual arrogant pose hasn't changed."
    },
    {
        "message": "East River, huh,"
    },
    {
        "message": "how far did they go to buy those buns?"
    },
    {
        "message": "?"
    },
    {
        "message": "Are you okay?"
    },
    {
        "message": "Oh no,"
    },
    {
        "message": "Boss!"
    },
    {
        "message": "You’re so relaxed at a time like this!"
    },
    {
        "message": "Even if you say it’s a big deal or something serious, you can’t expect me to be shocked without knowing what's so serious, right?"
    },
    {
        "message": "Oh, right. I thought we had already talked about it. Ah, how embarrassing!"
    },
    {
        "message": "The world feels so chaotic right now."
    },
    {
        "message": "So, what happened?"
    },
    {
        "message": "Well, um,"
    },
    {
        "message": "they found Ginny's corpse in the East River!"
    },
    {
        "message": "Ginny's corpse was found!?"
    },
    {
        "message": "Yes, that's right!!!"
    },
    {
        "message": "They say she was missing an arm."
    },
    {
        "message": "It was a corpse with no left arm."
    },
    {
        "message": "So she really was dead, huh?"
    },
    {
        "message": "I see."
    },
    {
        "message": "When Guy and the others went on their trip, Ginny's corpse was discovered."
    },
    {
        "message": "Oh, no way! Could it be that Guy and the others are the culprits and fled the country like this?"
    },
    {
        "message": "That can't be true, right?"
    },
    {
        "message": "Ginny was killed quite a while ago, the police officer who was at the scene said."
    },
    {
        "message": "Where did Guy and the others go on their trip?"
    },
    {
        "message": "Well, that's the thing,"
    },
    {
        "message": "I missed asking about it."
    },
    {
        "message": "I don't mean to say this,"
    },
    {
        "message": "but doesn't that seem suspicious?"
    },
    {
        "message": "I mean, it’s been all people linked to Guy or Kristy that have been killed."
    },
    {
        "message": "Kristy must have been resenting the women involved with Guy, right?"
    },
    {
        "message": "But then again, there's no evidence that she definitely did it."
    },
    {
        "message": "Still, when you think about it, it's a bit weird that only people connected to Kristy and Guy are being killed."
    },
    {
        "message": "Could it be that Kristy is..."
    },
    {
        "message": "※※※　Bug　※※※"
    },
    {
        "message": "Ｖ＝"
    },
    {
        "message": "　Ｎ＝"
    }
]