[
    {
        "message": "Jake"
    },
    {
        "message": "Fabar"
    },
    {
        "message": "Günter"
    },
    {
        "message": "　　　　　　　　　　− The next day −"
    },
    {
        "message": "I found it strangely concerning that Jennifer was"
    },
    {
        "message": "going to see someone."
    },
    {
        "message": "It might be because I had gotten closer to her again, or it could be that I wanted to know her better."
    },
    {
        "message": "So, would I be able to"
    },
    {
        "message": "have an interview today?"
    },
    {
        "message": "With such anxieties in mind,"
    },
    {
        "message": "I visited his place, and fortunately, I was able to catch him."
    },
    {
        "message": "I'm about to head out, so please make it quick."
    },
    {
        "message": "Sorry, I have something I wanted to ask."
    },
    {
        "message": "Now, what exactly is the matter today? Miss Dern has already passed away; is there still something?"
    },
    {
        "message": "I truly apologize for bothering you when you’re busy, but I’d like to talk to you about Jennifer."
    },
    {
        "message": "Jennifer?"
    },
    {
        "message": "The actress Jennifer Rumford, she's been getting counseling here."
    },
    {
        "message": "Mr. Snipes, I would like to clarify that I am a psychiatrist, not your personal source of information."
    },
    {
        "message": "I think I understand that well enough. However, regarding her symptoms,"
    },
    {
        "message": "I sought your cooperation as a friend in Miss Dern's case to help her."
    },
    {
        "message": "However, it seems that Jennifer Rumford is here primarily for stress relief."
    },
    {
        "message": "Saying she’s here for stress relief implies there must have been something in the past?"
    },
    {
        "message": "I have nothing more to say. Please leave. I am a very busy person."
    },
    {
        "message": "　　ＲＲＲＲＲＲＲＲＲＲＲＲＲ"
    },
    {
        "message": "Excuse me?"
    },
    {
        "message": "Yuriko"
    },
    {
        "message": "Hello, is this the Boss?"
    },
    {
        "message": "Yuriko"
    },
    {
        "message": "What’s up?"
    },
    {
        "message": "Yuriko"
    },
    {
        "message": "It's bad, it's really bad!"
    },
    {
        "message": "Calm down, what happened?"
    },
    {
        "message": "Yuriko"
    },
    {
        "message": "Patricia has"
    },
    {
        "message": "been murdered, the director's daughter!"
    },
    {
        "message": "The director never dreamed, right after Guy and Kristy's funeral, he would have to hold his daughter's funeral."
    },
    {
        "message": "I waited for the director to calm down and then visited his private residence in New York."
    },
    {
        "message": "The director"
    },
    {
        "message": "This time, all I can say is"
    },
    {
        "message": "please don't say any more than that."
    },
    {
        "message": "I still can't bring myself to accept that something happened to her."
    },
    {
        "message": "The director"
    },
    {
        "message": "looked as if he had aged ten years."
    },
    {
        "message": "The empty room appeared lifeless, seeming to reflect its owner's lack of vitality."
    },
    {
        "message": "It's terrible."
    },
    {
        "message": "The corpse, known as Patricia, was missing its head."
    },
    {
        "message": "What!?!"
    },
    {
        "message": "Even if her clothes and belongings were hers, there's no way to recognize her without her face."
    },
    {
        "message": "That was a shocking truth."
    },
    {
        "message": "Patricia had been decapitated by the murderer."
    },
    {
        "message": "This means the perpetrator is the same as in the previous serial murder cases."
    },
    {
        "message": "Don't you think this must be the work of someone who has killed before?"
    },
    {
        "message": "It seems that's a possibility."
    },
    {
        "message": "You, do you have any leads? Don't you know who the killer is?"
    },
    {
        "message": "Unfortunately, not yet."
    },
    {
        "message": "Anyone will do, just bring the killer to me."
    },
    {
        "message": "Then I'll cut off their head."
    },
    {
        "message": "Saying this, the director collapsed on the floor, continuously calling out Patricia's name."
    },
    {
        "message": "I stood there helplessly, embracing the director's shoulders."
    }
]